MANIFEST.in
README.md
setup.cfg
setup.py
stopforumspam_api/__init__.py
stopforumspam_api.egg-info/PKG-INFO
stopforumspam_api.egg-info/SOURCES.txt
stopforumspam_api.egg-info/dependency_links.txt
stopforumspam_api.egg-info/top_level.txt