Metadata-Version: 1.1
Name: stopforumspam-api
Version: 0.0.3
Summary: Basic interface for Stop Forum Spam API
Home-page: UNKNOWN
Author: Stephen Paulger
Author-email: stephen.paulger@newspeak.org.uk
License: UNKNOWN
Platform: UNKNOWN
Classifier: Development Status :: 2 - Pre-Alpha
Classifier: Environment :: Web Environment
Classifier: Intended Audience :: Developers
Classifier: Operating System :: OS Independent
Classifier: Programming Language :: Python
Classifier: Topic :: Internet :: WWW/HTTP :: Dynamic Content
Classifier: Topic :: Internet :: WWW/HTTP :: Site Management
